pipupgrade/VERSION
pipupgrade/__attr__.py
pipupgrade/__init__.py
pipupgrade/__main__.py
pipupgrade/_compat.py
pipupgrade/_pip.py
pipupgrade/cache.py
pipupgrade/config.py
pipupgrade/exception.py
pipupgrade/pipupgrade.py
pipupgrade/pubgrub.py
pipupgrade/semver.py
pipupgrade/cli/__init__.py
pipupgrade/cli/parser.py
pipupgrade/commands/__init__.py
pipupgrade/commands/helper.py
pipupgrade/commands/util.py
pipupgrade/commands/util/__init__.py
pipupgrade/data/bootstrap.sql
pipupgrade/jobs/__init__.py
pipupgrade/jobs/build_dependency_tree.py
pipupgrade/jobs/build_proxy_list.py
pipupgrade/model/__init__.py
pipupgrade/model/package.py
pipupgrade/model/project.py
pipupgrade/model/registry.py
pipupgrade-1.12.0.dist-info/AUTHORS.md
pipupgrade-1.12.0.dist-info/LICENSE
pipupgrade-1.12.0.dist-info/METADATA
pipupgrade-1.12.0.dist-info/WHEEL
pipupgrade-1.12.0.dist-info/entry_points.txt
pipupgrade-1.12.0.dist-info/top_level.txt
pipupgrade-1.12.0.dist-info/RECORD
