Metadata-Version: 2.1
Name: pipupgrade
Version: 1.12.0
Summary: UPGRADE ALL THE PIP PACKAGES!
Home-page: https://github.com/achillesrasquinha/pipupgrade
Author: Achilles Rasquinha
Author-email: achillesrasquinha@gmail.com
License: MIT
Keywords: pip update upgrade cli command
Platform: UNKNOWN
Classifier: Development Status :: 5 - Production/Stable
Classifier: Environment :: Console
Classifier: Intended Audience :: Developers
Classifier: License :: OSI Approved :: MIT License
Classifier: Programming Language :: Python :: 2
Classifier: Programming Language :: Python :: 2.7
Classifier: Programming Language :: Python :: 3
Classifier: Programming Language :: Python :: 3.4
Classifier: Programming Language :: Python :: 3.5
Classifier: Programming Language :: Python :: 3.6
Classifier: Programming Language :: Python :: 3.7
Classifier: Programming Language :: Python :: 3.8
Classifier: Programming Language :: Python :: 3.9
Classifier: Programming Language :: Python :: 3.10
Classifier: Programming Language :: Python :: Implementation :: CPython
Classifier: Programming Language :: Python :: Implementation :: PyPy
Provides-Extra: dev
License-File: LICENSE
License-File: AUTHORS.md
